pwdusage/__init__.py
pwdusage/base_agent.py
pwdusage/common.py
pwdusage/engine.py
pwdusage/example_usage.json
pwdusage/server.py
pwdusage/simple_agent.py
pwdusage-1.0.1.dist-info/METADATA
pwdusage-1.0.1.dist-info/WHEEL
pwdusage-1.0.1.dist-info/licenses/LICENSE
pwdusage-1.0.1.dist-info/RECORD
