Metadata-Version: 2.4
Name: pwdusage
Version: 1.0.1
Summary: Usage (mainly time of use) proxy microservice for Powerwall-Dashboard.
Project-URL: Homepage, https://github.com/BuongiornoTexas/pwdusage
Project-URL: Bug Tracker, https://github.com/BuongiornoTexas/pwdusage/issues
Author: BuongiornoTexas
License-File: LICENSE
Classifier: License :: OSI Approved :: MIT License
Classifier: Operating System :: OS Independent
Classifier: Programming Language :: Python :: 3
Requires-Python: >=3.11
Requires-Dist: influxdb-client[extra]
Requires-Dist: simplejson
